next_json/__init__.py
next_json/event_emitter.py
next_json/next_config_manager.py
next_json/next_json_obj.py
next_json-0.0.8.dist-info/LICENSE
next_json-0.0.8.dist-info/METADATA
next_json-0.0.8.dist-info/WHEEL
next_json-0.0.8.dist-info/top_level.txt
next_json-0.0.8.dist-info/RECORD
