Metadata-Version: 2.1
Name: next_json
Version: 0.0.8
Summary: Json and config file manage system
Author: Rymfader
Project-URL: Homepage, https://github.com/Rymfader/next_json
Project-URL: Issues, https://github.com/Rymfader/next_json/issues
Classifier: Programming Language :: Python :: 3
Classifier: License :: OSI Approved :: MIT License
Classifier: Operating System :: OS Independent
Requires-Python: >=3.6
License-File: LICENSE
